femtotemplate/ENV_REQUIREMENTS.sh
femtotemplate/PY_REQUIREMENTS
femtotemplate/VERSION
femtotemplate/__init__.py
femtotemplate/names.py
femtotemplate-0.7.19.dist-info/licenses/LICENSE
test/__init__.py
test/test_names.py
test/test_package.py
femtotemplate-0.7.19.dist-info/METADATA
femtotemplate-0.7.19.dist-info/WHEEL
femtotemplate-0.7.19.dist-info/top_level.txt
femtotemplate-0.7.19.dist-info/RECORD
