Metadata-Version: 2.4
Name: femtotemplate
Version: 0.7.19
Summary: Femtosense template project
Home-page: https://github.com/femtosense/femtotemplate
Author: Femtosense
Author-email: info@femtosense.ai
Project-URL: Source, https://github.com/femtosense/femtotemplate
Classifier: Development Status :: 3 - Alpha
Classifier: Intended Audience :: Developers
Classifier: Programming Language :: Python :: 3.10
Classifier: Programming Language :: Python :: 3 :: Only
Classifier: Operating System :: OS Independent
Requires-Python: >=3.6
License-File: LICENSE
Requires-Dist: Cython
Requires-Dist: numpy>=1.18.0
Dynamic: author
Dynamic: author-email
Dynamic: classifier
Dynamic: description
Dynamic: description-content-type
Dynamic: home-page
Dynamic: license-file
Dynamic: project-url
Dynamic: requires-dist
Dynamic: requires-python
Dynamic: summary
